zsl_ma/__init__.py
zsl_ma/main.py
zsl_ma/model.py
zsl_ma/predict.py
zsl_ma/version.py
zsl_ma/dataset_utils/CustomImageDataset.py
zsl_ma/dataset_utils/FactorLabelMapper.py
zsl_ma/dataset_utils/__init__.py
zsl_ma/dataset_utils/dataset.py
zsl_ma/dataset_utils/em_dataset.py
zsl_ma/models/CNN.py
zsl_ma/models/DisentangledModel.py
zsl_ma/models/VAE.py
zsl_ma/models/__init__.py
zsl_ma/models/kan.py
zsl_ma/models/projection.py
zsl_ma/tools/Losses.py
zsl_ma/tools/__init__.py
zsl_ma/tools/distributed_utils.py
zsl_ma/tools/plot.py
zsl_ma/tools/predict_untils.py
zsl_ma/tools/process_single_npy.py
zsl_ma/tools/tool.py
zsl_ma/tools/train_val_until.py
zsl_ma/train/AI_train.py
zsl_ma/train/__init__.py
zsl_ma/train/predict.py
zsl_ma/train/train.py
zsl_ma/train/train_att_proj.py
zsl_ma/train/train_cae.py
zsl_ma/train/train_cls.py
zsl_ma/train/train_disent.py
zsl_ma/train/train_em.py
zsl_ma/train/train_fea_proj.py
zsl_ma/ttf/Arial.ttf
zsl_ma/ttf/SimHei.ttf
zsl_ma/ttf/TimesNewRoman.ttf
zsl_ma-0.1.5.dist-info/licenses/LICENSE
zsl_ma-0.1.5.dist-info/METADATA
zsl_ma-0.1.5.dist-info/WHEEL
zsl_ma-0.1.5.dist-info/top_level.txt
zsl_ma-0.1.5.dist-info/RECORD
