Metadata-Version: 2.4
Name: zsl_ma
Version: 0.1.5
Summary: My awesome package
Author-email: yms <11@qq.com>
License-Expression: MIT
License-File: LICENSE
Dynamic: license-file
